odoo8_addon_web_graph_sort-8.0.1.0.0.99.dev7-py2.7-nspkg.pth
odoo8_addon_web_graph_sort-8.0.1.0.0.99.dev7.dist-info/DESCRIPTION.rst
odoo8_addon_web_graph_sort-8.0.1.0.0.99.dev7.dist-info/METADATA
odoo8_addon_web_graph_sort-8.0.1.0.0.99.dev7.dist-info/RECORD
odoo8_addon_web_graph_sort-8.0.1.0.0.99.dev7.dist-info/WHEEL
odoo8_addon_web_graph_sort-8.0.1.0.0.99.dev7.dist-info/metadata.json
odoo8_addon_web_graph_sort-8.0.1.0.0.99.dev7.dist-info/namespace_packages.txt
odoo8_addon_web_graph_sort-8.0.1.0.0.99.dev7.dist-info/top_level.txt
odoo_addons/web_graph_sort/README.rst
odoo_addons/web_graph_sort/__init__.py
odoo_addons/web_graph_sort/__openerp__.py
odoo_addons/web_graph_sort/i18n/ar.po
odoo_addons/web_graph_sort/i18n/de.po
odoo_addons/web_graph_sort/i18n/es.po
odoo_addons/web_graph_sort/i18n/fi.po
odoo_addons/web_graph_sort/i18n/fr.po
odoo_addons/web_graph_sort/i18n/it.po
odoo_addons/web_graph_sort/i18n/pt_BR.po
odoo_addons/web_graph_sort/i18n/sl.po
odoo_addons/web_graph_sort/i18n/tr.po
odoo_addons/web_graph_sort/i18n/web_graph_sort.pot
odoo_addons/web_graph_sort/static/description/icon.png
odoo_addons/web_graph_sort/static/src/css/web_graph_sort.css
odoo_addons/web_graph_sort/static/src/js/web_graph_sort.js
odoo_addons/web_graph_sort/views/web_graph_sort.xml
